.DS_Store
publishutil/.DS_Store
publishutil/__init__.py
publishutil/figurelayout.py
publishutil/figure_layouts/nature.yml
matplotlib_publishutil-0.0.4.dist-info/LICENSE
matplotlib_publishutil-0.0.4.dist-info/METADATA
matplotlib_publishutil-0.0.4.dist-info/WHEEL
matplotlib_publishutil-0.0.4.dist-info/top_level.txt
matplotlib_publishutil-0.0.4.dist-info/RECORD
