Metadata-Version: 2.1
Name: matplotlib-publishutil
Version: 0.0.4
Summary: Utilities to help configure matplotlib figures for publication.
Home-page: https://github.com/tommct/matplotlib-publishutil
Author: Tom McTavish
Author-email: tom@spikes.ai
License: UNKNOWN
Project-URL: Bug Tracker, https://github.com/tommct/matplotlib-publishutil/issues
Platform: UNKNOWN
Classifier: Programming Language :: Python :: 3
Classifier: License :: OSI Approved :: MIT License
Classifier: Operating System :: OS Independent
Requires: matplotlib
Requires: pyaml
Requires-Python: >=3.6
License-File: LICENSE
